glanceclient/__init__.py
glanceclient/_i18n.py
glanceclient/client.py
glanceclient/exc.py
glanceclient/shell.py
glanceclient/common/__init__.py
glanceclient/common/exceptions.py
glanceclient/common/http.py
glanceclient/common/https.py
glanceclient/common/progressbar.py
glanceclient/common/utils.py
glanceclient/tests/__init__.py
glanceclient/tests/utils.py
glanceclient/tests/functional/README.rst
glanceclient/tests/functional/__init__.py
glanceclient/tests/functional/base.py
glanceclient/tests/functional/v1/__init__.py
glanceclient/tests/functional/v1/test_readonly_glance.py
glanceclient/tests/functional/v2/__init__.py
glanceclient/tests/functional/v2/test_http_headers.py
glanceclient/tests/functional/v2/test_readonly_glance.py
glanceclient/tests/unit/__init__.py
glanceclient/tests/unit/test_base.py
glanceclient/tests/unit/test_client.py
glanceclient/tests/unit/test_exc.py
glanceclient/tests/unit/test_http.py
glanceclient/tests/unit/test_progressbar.py
glanceclient/tests/unit/test_shell.py
glanceclient/tests/unit/test_ssl.py
glanceclient/tests/unit/test_utils.py
glanceclient/tests/unit/v1/__init__.py
glanceclient/tests/unit/v1/test_image_members.py
glanceclient/tests/unit/v1/test_images.py
glanceclient/tests/unit/v1/test_shell.py
glanceclient/tests/unit/v1/test_versions.py
glanceclient/tests/unit/v2/__init__.py
glanceclient/tests/unit/v2/base.py
glanceclient/tests/unit/v2/fixtures.py
glanceclient/tests/unit/v2/test_cache.py
glanceclient/tests/unit/v2/test_client_requests.py
glanceclient/tests/unit/v2/test_images.py
glanceclient/tests/unit/v2/test_info.py
glanceclient/tests/unit/v2/test_members.py
glanceclient/tests/unit/v2/test_metadefs_namespaces.py
glanceclient/tests/unit/v2/test_metadefs_objects.py
glanceclient/tests/unit/v2/test_metadefs_properties.py
glanceclient/tests/unit/v2/test_metadefs_resource_types.py
glanceclient/tests/unit/v2/test_metadefs_tags.py
glanceclient/tests/unit/v2/test_schemas.py
glanceclient/tests/unit/v2/test_shell_v2.py
python_glanceclient-4.10.0.dist-info/AUTHORS
python_glanceclient-4.10.0.dist-info/LICENSE
python_glanceclient-4.10.0.dist-info/METADATA
python_glanceclient-4.10.0.dist-info/WHEEL
python_glanceclient-4.10.0.dist-info/entry_points.txt
python_glanceclient-4.10.0.dist-info/pbr.json
python_glanceclient-4.10.0.dist-info/top_level.txt
python_glanceclient-4.10.0.dist-info/RECORD
