Metadata-Version: 2.1
Name: python-glanceclient
Version: 4.10.0
Summary: OpenStack Image API Client Library
Home-page: https://docs.openstack.org/python-glanceclient/latest/
Author: OpenStack
Author-email: openstack-discuss@lists.openstack.org
License: Apache License, Version 2.0
Classifier: Development Status :: 5 - Production/Stable
Classifier: Environment :: Console
Classifier: Environment :: OpenStack
Classifier: Intended Audience :: Information Technology
Classifier: Intended Audience :: System Administrators
Classifier: License :: OSI Approved :: Apache Software License
Classifier: Operating System :: POSIX :: Linux
Classifier: Programming Language :: Python
Classifier: Programming Language :: Python :: Implementation :: CPython
Classifier: Programming Language :: Python :: 3 :: Only
Classifier: Programming Language :: Python :: 3
Classifier: Programming Language :: Python :: 3.10
Classifier: Programming Language :: Python :: 3.11
Classifier: Programming Language :: Python :: 3.12
Requires-Python: >=3.10
License-File: LICENSE
Requires-Dist: pbr!=2.1.0,>=2.0.0
Requires-Dist: PrettyTable>=0.7.1
Requires-Dist: keystoneauth1>=3.6.2
Requires-Dist: requests>=2.14.2
Requires-Dist: warlock>=1.2.0
Requires-Dist: oslo.utils>=3.33.0
Requires-Dist: oslo.i18n>=3.15.3
Requires-Dist: wrapt>=1.7.0
Requires-Dist: pyOpenSSL>=17.1.0
